fave_measurement_point/__init__.py
fave_measurement_point/formants.py
fave_measurement_point/heuristic.py
fave_measurement_point/processor.py
fave_measurement_point-0.1.5.dist-info/LICENSE
fave_measurement_point-0.1.5.dist-info/METADATA
fave_measurement_point-0.1.5.dist-info/WHEEL
fave_measurement_point-0.1.5.dist-info/RECORD
