Metadata-Version: 2.3
Name: fave-measurement-point
Version: 0.1.5
Summary: A library for defining and evaluating formant measurement point heuristics.
License: GPLv3
Author: JoFrhwld
Author-email: JoFrhwld@gmail.com
Requires-Python: >=3.10,<4.0
Classifier: License :: Other/Proprietary License
Classifier: Programming Language :: Python :: 3
Classifier: Programming Language :: Python :: 3.10
Classifier: Programming Language :: Python :: 3.11
Classifier: Programming Language :: Python :: 3.12
Classifier: Programming Language :: Python :: 3.13
Requires-Dist: numpy (<=2.2)
